kivy_garden/graph/__init__.py
kivy_garden/graph/_version.py
kivy_garden/graph/tests/test_import.py
kivy_garden.graph-0.4.0.dist-info/AUTHORS.txt
kivy_garden.graph-0.4.0.dist-info/LICENSE.txt
kivy_garden.graph-0.4.0.dist-info/METADATA
kivy_garden.graph-0.4.0.dist-info/WHEEL
kivy_garden.graph-0.4.0.dist-info/top_level.txt
kivy_garden.graph-0.4.0.dist-info/RECORD
